tkate/__init__.py
tkate/frames.py
tkate/version.py
tkate-0.7.1.dist-info/METADATA
tkate-0.7.1.dist-info/WHEEL
tkate-0.7.1.dist-info/top_level.txt
tkate-0.7.1.dist-info/RECORD
