Metadata-Version: 2.1
Name: tkate
Version: 0.7.1
Summary: A tkinter-based front-end GUI for trigger and monitoring hardware tests based on the ATE package
Home-page: https://github.com/slightlynybbled/tkate
Author: Jason R. Jones
Author-email: slightlynybbled@gmail.com
License: MIT
Platform: UNKNOWN
Classifier: License :: OSI Approved :: MIT License
Classifier: Development Status :: 3 - Alpha
Classifier: Programming Language :: Python
Classifier: Programming Language :: Python :: 3
Classifier: Programming Language :: Python :: 3.6
Classifier: Programming Language :: Python :: 3.7
Classifier: Programming Language :: Python :: Implementation :: CPython
Requires-Python: >=3.6.0
Requires-Dist: ate (>=0.18.0)
